LICENSE.rst
README.md
setup.cfg
setup.py
ravdl/__init__.py
ravdl/globals.py
ravdl/utils_singleton.py
ravdl.egg-info/PKG-INFO
ravdl.egg-info/SOURCES.txt
ravdl.egg-info/dependency_links.txt
ravdl.egg-info/requires.txt
ravdl.egg-info/top_level.txt
ravdl/utils/__init__.py
ravdl/utils/data_manipulation.py
ravdl/utils/data_operations.py
ravdl/utils/misc.py
ravdl/v2/NeuralNetwork.py
ravdl/v2/__init__.py
ravdl/v2/layers.py
ravdl/v2/load_onnx_model.py
ravdl/v2/optimizers.py
ravdl/v2/utils/__init__.py
ravdl/v2/utils/data_manipulation.py
ravdl/v2/utils/data_operations.py
ravdl/v2/utils/misc.py