Metadata-Version: 2.1
Name: ravdl
Version: 0.12
Summary: UNKNOWN
Home-page: https://github.com/ravenprotocol/ravdl
Author: Raven Protocol
Author-email: kailash@ravenprotocol.com
License: MIT
Keywords: Ravdl,deep learning library,algorithms
Platform: UNKNOWN
License-File: LICENSE.rst
